jasmin_telnet/__init__.py
jasmin_telnet/basicmanager.py
jasmin_telnet/conn.py
jasmin_telnet/exceptions.py
jasmin_telnet/filter.py
jasmin_telnet/group.py
jasmin_telnet/httpccm.py
jasmin_telnet/mointerceptor.py
jasmin_telnet/morouter.py
jasmin_telnet/mtinterceptor.py
jasmin_telnet/mtrouter.py
jasmin_telnet/proxy.py
jasmin_telnet/smppccm.py
jasmin_telnet/user.py
jasmin_telnet-0.0.32.dist-info/METADATA
jasmin_telnet-0.0.32.dist-info/WHEEL
jasmin_telnet-0.0.32.dist-info/licenses/LICENSE
jasmin_telnet-0.0.32.dist-info/RECORD
